{"artifacts":["origins/abiogenesis/geometric_semantic_braiding.py"],"canon_allowed":false,"content":{"artifacts":["origins/abiogenesis/geometric_semantic_braiding.py","tests/test_semantic_nucleic_braiding.py","paper/main.tex","paper/references.bib","reports/demo_trace_v03.json"],"certification_boundary":{"carbon_organic_scope":true,"empirical_abiogenesis_proof_claimed":false,"semantic_model_claimed":true,"thermodynamic_rna_folding_claimed":false},"iteration":"v03_noema_rewrite","meaning_candidate":{"canon_allowed":false,"confidence":0.78,"context_required":true,"hypothesis":"Carbon-organic nucleic-acid folding and semantic compression can be compared through fold/weave/knot invariants: recurrence, residue, closure, crossing, transition and retention.","needs_repair":false,"source":"local NOEMA CURRENT + Origins uploaded project files + deterministic v0.3 rewrite","uncertainty_operator":"chyba"},"namespace":"Origins-Of-Life","project_id":"Origins-Of-Life::semantic_nucleic_braiding","schema":"NOEMA_INGEST_CANDIDATE_V0_3","source_current_state_id":"NOEMA-20260517T021109-a97dc110e6"},"created_at_utc":"2026-05-17T02:27:26.743925+00:00","layer":"episodic","meaning_candidate":{"canon_allowed":false,"confidence":0.78,"context_required":true,"hypothesis":"Carbon-organic nucleic-acid folding and semantic compression can be compared through fold/weave/knot invariants: recurrence, residue, closure, crossing, transition and retention.","needs_repair":false,"source":"local NOEMA CURRENT + uploaded Origins ZIP + v03 rewrite","uncertainty_operator":"chyba"},"namespace":"Origins-Of-Life","previous_snap_hash":"6431f1b76028564e70729dd607ede7984aefa574b6070ecd7b653b5034e41952","project_id":"Origins-Of-Life::semantic_nucleic_braiding","schema":"NOEMA_MINIMAL_MONOLITH_V0_1","snap_hash":"2c3473d1e5efdf1fc8d403966bb1384eedb1237f4bb7bc4e1c19910f06e4bc60","snap_id":"NOEMA-20260517T022726-3fc21483ca","snap_type":"iteration_state","tags":["braiding","nucleic_acid","origins","semantic_compression"]}
